env_validator/__init__.py
env_validator/cli/main.py
env_validator/core/config.py
env_validator/core/types.py
env_validator/core/validator.py
env_validator/frameworks/__init__.py
env_validator/frameworks/django.py
env_validator/frameworks/fastapi.py
env_validator/frameworks/flask.py
env_validator/monitoring/__init__.py
env_validator/monitoring/drift.py
env_validator/monitoring/health.py
env_validator/monitoring/metrics.py
env_validator/security/__init__.py
env_validator/security/audit.py
env_validator/security/scanner.py
env_validator/utils/__init__.py
env_validator/utils/exporters.py
env_validator/utils/loaders.py
env_validator/validators/base.py
env_validator/validators/cloud.py
env_validator/validators/data.py
env_validator/validators/network.py
env_validator/validators/registry.py
env_validator/validators/security.py
envvar_validator-1.0.1.dist-info/licenses/LICENSE
envvar_validator-1.0.1.dist-info/METADATA
envvar_validator-1.0.1.dist-info/WHEEL
envvar_validator-1.0.1.dist-info/entry_points.txt
envvar_validator-1.0.1.dist-info/top_level.txt
envvar_validator-1.0.1.dist-info/RECORD
