Metadata-Version: 2.4
Name: envvar-validator
Version: 1.0.1
Summary: The most comprehensive, production-ready environment variable validation library for Python
Author-email: Sherin Joseph Roy <sherin.joseph2217@gmail.com>
Maintainer-email: Sherin Joseph Roy <sherin.joseph2217@gmail.com>
License-Expression: MIT
Project-URL: Homepage, https://github.com/Sherin-SEF-AI/env-validator
Project-URL: Documentation, https://env-validator.readthedocs.io
Project-URL: Repository, https://github.com/Sherin-SEF-AI/env-validator.git
Project-URL: Bug Tracker, https://github.com/Sherin-SEF-AI/env-validator/issues
Project-URL: Source Code, https://github.com/Sherin-SEF-AI/env-validator
Project-URL: Changelog, https://github.com/Sherin-SEF-AI/env-validator/blob/main/CHANGELOG.md
Keywords: environment,validation,env,variables,configuration,settings,security,compliance,monitoring,cli
Classifier: Development Status :: 5 - Production/Stable
Classifier: Intended Audience :: Developers
Classifier: Operating System :: OS Independent
Classifier: Programming Language :: Python :: 3
Classifier: Programming Language :: Python :: 3.8
Classifier: Programming Language :: Python :: 3.9
Classifier: Programming Language :: Python :: 3.10
Classifier: Programming Language :: Python :: 3.11
Classifier: Programming Language :: Python :: 3.12
Classifier: Topic :: Software Development :: Libraries :: Python Modules
Classifier: Topic :: System :: Systems Administration
Classifier: Topic :: Utilities
Classifier: Framework :: Django
Classifier: Framework :: Flask
Classifier: Framework :: FastAPI
Classifier: Environment :: Console
Classifier: Environment :: Web Environment
Requires-Python: >=3.8
License-File: LICENSE
Requires-Dist: pydantic>=2.0.0
Requires-Dist: python-dotenv>=1.0.0
Requires-Dist: pyyaml>=6.0
Requires-Dist: toml>=0.10.2
Requires-Dist: click>=8.0.0
Requires-Dist: rich>=13.0.0
Requires-Dist: typer>=0.9.0
Requires-Dist: email-validator>=2.0.0
Requires-Dist: dnspython>=2.3.0
Requires-Dist: cryptography>=41.0.0
Requires-Dist: psutil>=5.9.0
Requires-Dist: requests>=2.31.0
Requires-Dist: jinja2>=3.1.0
Requires-Dist: colorama>=0.4.6
Requires-Dist: packaging>=23.0
Requires-Dist: pathlib2>=2.3.7; python_version < "3.4"
Provides-Extra: dev
Requires-Dist: pytest>=7.0.0; extra == "dev"
Requires-Dist: pytest-cov>=4.0.0; extra == "dev"
Requires-Dist: pytest-mock>=3.10.0; extra == "dev"
Requires-Dist: pytest-asyncio>=0.21.0; extra == "dev"
Requires-Dist: black>=23.0.0; extra == "dev"
Requires-Dist: isort>=5.12.0; extra == "dev"
Requires-Dist: flake8>=6.0.0; extra == "dev"
Requires-Dist: mypy>=1.0.0; extra == "dev"
Requires-Dist: pre-commit>=3.0.0; extra == "dev"
Requires-Dist: tox>=4.0.0; extra == "dev"
Requires-Dist: sphinx>=7.0.0; extra == "dev"
Requires-Dist: sphinx-rtd-theme>=1.3.0; extra == "dev"
Requires-Dist: myst-parser>=2.0.0; extra == "dev"
Provides-Extra: django
Requires-Dist: django>=4.0.0; extra == "django"
Provides-Extra: flask
Requires-Dist: flask>=2.3.0; extra == "flask"
Provides-Extra: fastapi
Requires-Dist: fastapi>=0.100.0; extra == "fastapi"
Requires-Dist: uvicorn>=0.23.0; extra == "fastapi"
Provides-Extra: monitoring
Requires-Dist: prometheus-client>=0.17.0; extra == "monitoring"
Requires-Dist: datadog>=0.44.0; extra == "monitoring"
Requires-Dist: newrelic>=8.0.0; extra == "monitoring"
Provides-Extra: security
Requires-Dist: bandit>=1.7.0; extra == "security"
Requires-Dist: safety>=2.3.0; extra == "security"
Provides-Extra: cloud
Requires-Dist: boto3>=1.28.0; extra == "cloud"
Requires-Dist: google-cloud-secret-manager>=2.16.0; extra == "cloud"
Requires-Dist: azure-keyvault-secrets>=4.7.0; extra == "cloud"
Dynamic: license-file
